{
    "Position": [
        7.1,
        4.4,
        -8.0
    ],
    "Rotation": [
        200.0,
        0.0,
        -20.0
    ],
    "PanTiltDirection": [
        0.0,
        -90.0
    ],
    "DataPointsTop": [
        {
            "Target": [
                8.5,
                3.15,
                -0.2
            ],
            "PanTilt": [
                -9.7,
                -21.82
            ],
            "PanTiltOffset": [
                175.91172790527344,
                226.0886993408203
            ],
            "Distance": null,
            "HomogTarget": 0
        },
        {
            "Target": [
                8.63,
                3.15,
                -7.17
            ],
            "PanTilt": [
                -62.12,
                -1.4000000000000015
            ],
            "PanTiltOffset": [
                180.38128662109375,
                172.59120178222656
            ],
            "Distance": 2.14296555519104,
            "HomogTarget": 0
        },
        {
            "Target": [
                0.475,
                3.15,
                -7.28
            ],
            "PanTilt": [
                74.7,
                23.9
            ],
            "PanTiltOffset": [
                -182.42636108398438,
                129.96359252929688
            ],
            "Distance": null,
            "HomogTarget": 0
        },
        {
            "Target": [
                0.45,
                3.15,
                -0.39
            ],
            "PanTilt": [
                38.7,
                -1.3000000000000018
            ],
            "PanTiltOffset": [
                -183.75445556640625,
                177.70639038085938
            ],
            "Distance": null,
            "HomogTarget": 0
        }
    ],
    "DataPointsBtm": [
        {
            "Target": [
                8.5,
                0.4,
                -0.2
            ],
            "PanTilt": [
                -14.099999999999998,
                -4.2
            ],
            "PanTiltOffset": [
                176.37229919433594,
                191.05474853515625
            ],
            "Distance": null,
            "HomogTarget": 0
        },
        {
            "Target": [
                8.63,
                0.4,
                -7.17
            ],
            "PanTilt": [
                -51.2,
                34.9
            ],
            "PanTiltOffset": [
                175.11572265625,
                105.91070556640625
            ],
            "Distance": null,
            "HomogTarget": 0
        },
        {
            "Target": [
                0.475,
                0.4,
                -7.28
            ],
            "PanTilt": [
                61.041,
                41.6
            ],
            "PanTiltOffset": [
                -180.44223022460938,
                94.23623657226562
            ],
            "Distance": null,
            "HomogTarget": 0
        },
        {
            "Target": [
                0.45,
                0.4,
                -0.39
            ],
            "PanTilt": [
                30.8,
                11.1
            ],
            "PanTiltOffset": [
                -182.89015197753906,
                152.511962890625
            ],
            "Distance": null,
            "HomogTarget": 0
        }
    ],
    "HomographyTop": [
        [
            -0.11369851640900609,
            0.007514758040533994,
            0.8168722091205854
        ],
        [
            -0.03994175582222359,
            -0.05138272324860128,
            -0.029750457132310917
        ],
        [
            -0.011083455668836536,
            0.11002819139421358,
            1.0
        ]
    ],
    "HomographyBtm": [
        [
            -0.09911245372427001,
            0.005793972624298153,
            0.617939109732707
        ],
        [
            -0.03454119055040006,
            -0.0462280750233432,
            0.21632677664602648
        ],
        [
            -0.009675185065378318,
            0.09654480850068696,
            1.0
        ]
    ],
    "HomographySide_1": [
        [
            0.03622027227137694,
            0.006815628249099368,
            -0.2542366346699317
        ],
        [
            -0.09584566389388771,
            -0.04749361187858522,
            -0.04384125153998933
        ],
        [
            -0.04802256953121802,
            0.10442639771895156,
            1.0
        ]
    ],
    "HomographySide_2": [
        [
            0.036488977521619496,
            0.007013414970399807,
            0.5518507827997435
        ],
        [
            -0.08730585334641619,
            -0.0445549258721175,
            0.23353512832577925
        ],
        [
            -0.04245712255869006,
            0.0958536317999006,
            0.9999999999999999
        ]
    ],
    "Axis": "z",
    "DMXStartingAddress": 136
}