{
    "Position": [
        9.1,
        1.5,
        -9.2
    ],
    "Rotation": [
        0.0,
        180.0,
        20.0
    ],
    "PanTiltDirection": [
        0.0,
        -90.0
    ],
    "DataPointsTop": [
        {
            "Target": [
                8.5,
                3.15,
                -0.2
            ],
            "PanTilt": [
                3.961,
                10.590000000000003
            ],
            "PanTiltOffset": [
                -183.95770263671875,
                158.3714599609375
            ],
            "Distance": null,
            "HomogTarget": 0
        },
        {
            "Target": [
                8.63,
                3.15,
                -7.17
            ],
            "PanTilt": [
                17.261,
                41.54
            ],
            "PanTiltOffset": [
                -193.80270385742188,
                98.38134765625
            ],
            "Distance": null,
            "HomogTarget": 0
        },
        {
            "Target": [
                0.475,
                3.15,
                -7.28
            ],
            "PanTilt": [
                -74.2,
                30.7
            ],
            "PanTiltOffset": [
                178.48533630371094,
                119.25591278076172
            ],
            "Distance": null,
            "HomogTarget": 0
        },
        {
            "Target": [
                0.45,
                3.15,
                -0.39
            ],
            "PanTilt": [
                -37.89999999999999,
                20.69
            ],
            "PanTiltOffset": [
                177.25155639648438,
                138.08810424804688
            ],
            "Distance": 12.456367492675781,
            "HomogTarget": 0
        }
    ],
    "DataPointsBtm": [
        {
            "Target": [
                8.5,
                0.4,
                -0.2
            ],
            "PanTilt": [
                -1.5,
                -5.7
            ],
            "PanTiltOffset": [
                175.5371551513672,
                190.9309539794922
            ],
            "Distance": null,
            "HomogTarget": 0
        },
        {
            "Target": [
                8.63,
                0.4,
                -7.17
            ],
            "PanTilt": [
                -9.739,
                -24.509999999999998
            ],
            "PanTiltOffset": [
                167.79470825195312,
                226.254638671875
            ],
            "Distance": null,
            "HomogTarget": 0
        },
        {
            "Target": [
                0.475,
                0.4,
                -7.28
            ],
            "PanTilt": [
                -75.9,
                12.200000000000001
            ],
            "PanTiltOffset": [
                178.65597534179688,
                155.37240600585938
            ],
            "Distance": null,
            "HomogTarget": 0
        },
        {
            "Target": [
                0.45,
                0.4,
                -0.39
            ],
            "PanTilt": [
                -41.3,
                8.2
            ],
            "PanTiltOffset": [
                177.31060791015625,
                162.86679077148438
            ],
            "Distance": 12.3955078125,
            "HomogTarget": 0
        }
    ],
    "HomographyTop": [
        [
            0.10061615084038684,
            0.002426275460639606,
            -0.7889599656244519
        ],
        [
            -0.034710767365158615,
            -0.0016421058214706652,
            0.47278522187711586
        ],
        [
            -0.0033301006898773335,
            0.10764983075937185,
            0.9999999999999999
        ]
    ],
    "HomographyBtm": [
        [
            0.10121404484438774,
            0.0031145751820687443,
            -0.8843954982544662
        ],
        [
            -0.03445314669179917,
            -0.0012968217355538068,
            0.19841443891806432
        ],
        [
            -0.004151915635666377,
            0.10745380544335872,
            1.0
        ]
    ],
    "HomographySide_1": [
        [
            0.042181176111021575,
            -0.0023077642808674286,
            -0.04386637760957412
        ],
        [
            0.12484213641930017,
            -0.010474898641953102,
            -0.1532002748398567
        ],
        [
            0.10139276494750653,
            0.1366370634440893,
            0.9999999999999999
        ]
    ],
    "HomographySide_2": [
        [
            0.03491281381066835,
            0.0008011307893075916,
            -0.8550933424467074
        ],
        [
            0.09984787420968788,
            -0.0007388737700470385,
            0.14348957662924616
        ],
        [
            -8.882587936898618e-05,
            0.10813498417172493,
            1.0
        ]
    ],
    "Axis": "z",
    "DMXStartingAddress": 190
}